{
  "id": 20022,
  "zone_id": 200,
  "name": "Main Room",
  "description": "In the clutter of the main room of the Wayhouse, is a path leading out from the\nkitchen to the east.  A wide archway allows admittance to the back room, from\nwhich you hear the distant clank of a pan hitting another.  There aren't very\nmany tables here, due to the amount of traffic coming in and out.",
  "header_raw": "200 8 1",
  "flags_text": "8",
  "sector": 1,
  "exits": [
    {
      "dir": 0,
      "description": "",
      "keywords": "",
      "door_flag": 0,
      "key": 0,
      "to": 20019
    },
    {
      "dir": 1,
      "description": "",
      "keywords": "",
      "door_flag": 0,
      "key": 0,
      "to": 20023
    },
    {
      "dir": 2,
      "description": "",
      "keywords": "",
      "door_flag": 0,
      "key": 0,
      "to": 20027
    },
    {
      "dir": 3,
      "description": "",
      "keywords": "",
      "door_flag": 0,
      "key": 0,
      "to": 20021
    }
  ],
  "extra_descriptions": [],
  "source_path": "/Users/ricardobussacro/Documents/Wardome/wdii/lib/world/wld/200.wld"
}