{
  "id": 2356,
  "zone_id": 23,
  "name": "The frigid wastelands",
  "description": "You wander through the frigid wastelands. Your breath is a cloud before you.\nThe cold cuts to the bone. Swirling snow and wind make it impossible for you\nto discern any directions.",
  "header_raw": "23 0 5",
  "flags_text": "0",
  "sector": 5,
  "exits": [
    {
      "dir": 0,
      "description": "",
      "keywords": "",
      "door_flag": 0,
      "key": 0,
      "to": 2354
    },
    {
      "dir": 1,
      "description": "",
      "keywords": "",
      "door_flag": 0,
      "key": 0,
      "to": 2355
    },
    {
      "dir": 2,
      "description": "",
      "keywords": "",
      "door_flag": 0,
      "key": 0,
      "to": 2359
    },
    {
      "dir": 3,
      "description": "",
      "keywords": "",
      "door_flag": 0,
      "key": 0,
      "to": 2355
    }
  ],
  "extra_descriptions": [],
  "source_path": "/Users/ricardobussacro/Documents/Wardome/wdii/lib/world/wld/23.wld"
}