{
  "id": 24509,
  "zone_id": 245,
  "name": "MaGog",
  "description": "You are in Satan's city of MaGog. About you writhe and cavort sinners in\na final frolic before destruction.Refuse and offal are the perfume of the city.\nDeterioration and decay claim every building you view.",
  "header_raw": "245 0 1",
  "flags_text": "0",
  "sector": 1,
  "exits": [
    {
      "dir": 0,
      "description": "MaGog",
      "keywords": "",
      "door_flag": 0,
      "key": 0,
      "to": 24523
    },
    {
      "dir": 3,
      "description": "MaGog",
      "keywords": "",
      "door_flag": 0,
      "key": 0,
      "to": 24508
    }
  ],
  "extra_descriptions": [],
  "source_path": "/Users/ricardobussacro/Documents/Wardome/wdii/lib/world/wld/245.wld"
}