{
  "id": 2681,
  "zone_id": 25,
  "name": "The Treasury",
  "description": "You are in a small chamber, the stale air here is testament to the fact\nthat it has gone undisturbed for many years.",
  "header_raw": "25 72 0",
  "flags_text": "72",
  "sector": 0,
  "exits": [
    {
      "dir": 3,
      "description": "",
      "keywords": "door secret",
      "door_flag": 1,
      "key": -1,
      "to": 2680
    }
  ],
  "extra_descriptions": [],
  "source_path": "/Users/ricardobussacro/Documents/Wardome/wdii/lib/world/wld/25.wld"
}