{
  "id": 30005,
  "zone_id": 300,
  "name": "A square with a statue",
  "description": "In the middle of the street is a tremendous statue.  Standing about 15 feet\ntall is a perfect stone rendition of Gil-Galad (an elven lord of ancient days).\nAt the foot of the statue is a brass plaque with writing in a flowing script\nupon it.",
  "header_raw": "300 8 1",
  "flags_text": "8",
  "sector": 1,
  "exits": [
    {
      "dir": 0,
      "description": "",
      "keywords": "",
      "door_flag": 0,
      "key": 0,
      "to": 30010
    },
    {
      "dir": 1,
      "description": "",
      "keywords": "",
      "door_flag": 0,
      "key": 0,
      "to": 30003
    },
    {
      "dir": 3,
      "description": "",
      "keywords": "",
      "door_flag": 0,
      "key": 0,
      "to": 30006
    },
    {
      "dir": 5,
      "description": "",
      "keywords": "",
      "door_flag": 0,
      "key": 0,
      "to": 30076
    }
  ],
  "extra_descriptions": [],
  "source_path": "/Users/ricardobussacro/Documents/Wardome/wdii/lib/world/wld/300.wld"
}