{
  "id": 3806,
  "zone_id": 38,
  "name": "A Small Storage Room",
  "description": "You are in a small storage room.  A pile of rags is against the far wall.  You\nthink you saw something move in the pile of rags!  The exit is to the west.",
  "header_raw": "38 8 0",
  "flags_text": "8",
  "sector": 0,
  "exits": [
    {
      "dir": 3,
      "description": "",
      "keywords": "door",
      "door_flag": 1,
      "key": -1,
      "to": 3802
    }
  ],
  "extra_descriptions": [],
  "source_path": "/Users/ricardobussacro/Documents/Wardome/wdii/lib/world/wld/38.wld"
}