{
  "id": 6372,
  "zone_id": 63,
  "name": "The Single Spider Line",
  "description": "A single spider line supports you once more.  The shack comes\ncloser into view and you are even more inclined to go back now.",
  "header_raw": "63 0 2",
  "flags_text": "0",
  "sector": 2,
  "exits": [
    {
      "dir": 0,
      "description": "",
      "keywords": "",
      "door_flag": 0,
      "key": -1,
      "to": 6371
    },
    {
      "dir": 2,
      "description": "",
      "keywords": "",
      "door_flag": 0,
      "key": -1,
      "to": 6373
    }
  ],
  "extra_descriptions": [],
  "source_path": "/Users/ricardobussacro/Documents/Wardome/wdii/lib/world/wld/63.wld"
}