{
  "id": 6720,
  "zone_id": 67,
  "name": "On a weathered stone terrace",
  "description": "This seems to be a plaza of sorts, but is so worn and cracked with age\nthe stone is barely holding together. Moss and weeds have all but \novergrown the rock-strewn surface. Balmy, roguish scents are drifting out\nof a dark, ivy-clothed building to the east.",
  "header_raw": "67 0 1",
  "flags_text": "0",
  "sector": 1,
  "exits": [
    {
      "dir": 0,
      "description": "",
      "keywords": "",
      "door_flag": 0,
      "key": -1,
      "to": 6722
    },
    {
      "dir": 1,
      "description": "",
      "keywords": "",
      "door_flag": 0,
      "key": -1,
      "to": 6721
    },
    {
      "dir": 2,
      "description": "",
      "keywords": "",
      "door_flag": 0,
      "key": -1,
      "to": 6723
    }
  ],
  "extra_descriptions": [],
  "source_path": "/Users/ricardobussacro/Documents/Wardome/wdii/lib/world/wld/67.wld"
}