{
  "id": 7907,
  "zone_id": 79,
  "name": "The Larder",
  "description": "You can see food all over.  Among the heaps of food you notice HUGE rats\nscuttling around, nibbling pieces off the heaps here and there.",
  "header_raw": "79 524 0",
  "flags_text": "524",
  "sector": 0,
  "exits": [
    {
      "dir": 2,
      "description": "",
      "keywords": "door wooden larder",
      "door_flag": 1,
      "key": -1,
      "to": 7906
    }
  ],
  "extra_descriptions": [],
  "source_path": "/Users/ricardobussacro/Documents/Wardome/wdii/lib/world/wld/79.wld"
}