{
  "id": 11247,
  "alias": "avatar asteh",
  "short_desc": "an avatar of Asteh",
  "long_desc": "A glowing humanoid stands trapped behind a shimmering force field.",
  "detailed_desc": "The avatar was summoned during the taking of the temple by the clergy\nin a last ditch effort to save their church. However the avatar was\novercome and entrapped here, where the faithful of No'ol can scorn and\nderide it. The force field bars only it from moving; all others may pass\nfreely. Her armor bears many dents, and her skin is burned badly in several\nplaces, punishment from her captors.",
  "flags_raw": "10 532648 450 E",
  "stats1_raw": "45 -20 -10 1d1+4500 5d9+108",
  "stats2_raw": "675 469801 9",
  "stats3_raw": "8 8 2 -1 -1",
  "source_path": "/Users/ricardobussacro/Documents/Wardome/wdii/lib/world/mob/112.mob"
}