{
  "id": 12228,
  "alias": "blodug-hofi",
  "short_desc": "Blodug-Hofi",
  "long_desc": "A magnificent brown horse rears up as you come near.",
  "detailed_desc": "The steed of Frey, it is a magnificent beast which serves its master\nloyally; even though it is no match for some of the greater enemies of\nthe Vanir, it will still stand over its master until slain.",
  "flags_raw": "10 271488 0 E",
  "stats1_raw": "30 -3 0 1d1+1800 5d4+52",
  "stats2_raw": "450 148261 4",
  "stats3_raw": "8 8 0 9 3",
  "source_path": "/Users/ricardobussacro/Documents/Wardome/wdii/lib/world/mob/122.mob"
}