{
  "id": 17603,
  "alias": "oldstyle jacklyn captain guard cityguard",
  "short_desc": "Captain Jacklyn",
  "long_desc": "Jacklyn, Captain of the Citadel Guard, is here raising morale.",
  "detailed_desc": "Jacklyn is pale and wiry, but then, so are most other witches.  The fact that\nJacklyn is a mage and a warrior makes her the perfect captain of the citadel\nguards.  Jacklyn is very beautiful, but whether it is due to her pale softness\nor her magic, no one has ever found out.  She isn't very strong physically, but\nshe need not be.",
  "flags_raw": "10 1073750024 1000 E",
  "stats1_raw": "30 5 5 1d1+630 5d4+12",
  "stats2_raw": "450 105901 0",
  "stats3_raw": "8 8 2 -1 -1",
  "source_path": "/Users/ricardobussacro/Documents/Wardome/wdii/lib/world/mob/176.mob"
}